{
  "$schema": "http://json-schema.org/draft-04/schema#",
  "type": "object",
  "properties": {
    "activation_statuses": {
      "type": "array",
      "id": "activation_statuses",
      "items": {
        "type": "object",
        "$ref": "activation_status.json"
      }
    },
    "total_records": {
      "type": "integer"
    },
    "first": {
      "type": "integer"
    },
    "last": {
      "type": "integer"
    }
  },
  "additionalProperties": false,
  "required": [
    "activation_statuses",
    "total_records"
  ]
}
